exmple/__init__.py
exmple/dateutils.py
lcutils/__init__.py
lcutils/dateutils.py
lcutils-0.0.5.dist-info/METADATA
lcutils-0.0.5.dist-info/WHEEL
lcutils-0.0.5.dist-info/top_level.txt
lcutils-0.0.5.dist-info/RECORD
